custom_iterable_dataset/__init__.py
custom_iterable_dataset/dataset.py
custom_iterable_dataset-0.1.0.dist-info/LICENSE
custom_iterable_dataset-0.1.0.dist-info/METADATA
custom_iterable_dataset-0.1.0.dist-info/WHEEL
custom_iterable_dataset-0.1.0.dist-info/top_level.txt
custom_iterable_dataset-0.1.0.dist-info/RECORD
