Metadata-Version: 2.2
Name: custom_iterable_dataset
Version: 0.1.0
Summary: A custom iterable dataset wrapper for use with Hugging Face's SFTTrainer.
Author-email: Parsa Bakhtiari <spacenavard1@gmail.com>
License:                                  Apache License
Requires-Python: >=3.8
License-File: LICENSE
Requires-Dist: torch>=2.0.0
Requires-Dist: transformers>=4.0.0
Requires-Dist: datasets>=2.0.0
Requires-Dist: trl>=0.13.0
Provides-Extra: test
Requires-Dist: pytest>=7.0.0; extra == "test"
Requires-Dist: pytest-cov>=4.0.0; extra == "test"
Provides-Extra: dev
Requires-Dist: build>=0.10.0; extra == "dev"
Requires-Dist: twine>=4.0.0; extra == "dev"
